{
  "title": "Kubernetes Workshop",
  "description": "Create kubernetes cluster",
  "backend": {
	"port": 30000,
	"imageid": "minikube"
   },
   "environment": {
	"uilayout": "terminal",
	"hideintro": false,
	"hidefinish": false
  },
  "difficulty": "beginner",
  "time": "2 minutes",
  "details": {
    "steps": [{
      "title": "Step 1 - Create cluster",
      "text": "step1.md"
    }],
    "intro": {
      "text": "intro.md",
      "credits": ""
    },
    "finish": {
      "text": "finish.md"
    }
  }
}
